llm_shell/__init__.py
llm_shell/bedrock_support.py
llm_shell/chatgpt_support.py
llm_shell/experimental_llm_agent.py
llm_shell/llm_shell.py
llm_shell/util.py
llm_shell-0.5.0.dist-info/LICENSE
llm_shell-0.5.0.dist-info/METADATA
llm_shell-0.5.0.dist-info/WHEEL
llm_shell-0.5.0.dist-info/entry_points.txt
llm_shell-0.5.0.dist-info/top_level.txt
llm_shell-0.5.0.dist-info/RECORD
