Metadata-Version: 2.1
Name: llm-shell
Version: 0.5.0
Summary: A Language Model Enhanced Command Line Interface
Home-page: https://github.com/mirror12k/llm-shell
Author: Mirror12k
License: MIT
Keywords: shell with integrated access to chatgpt or other llms
Classifier: Programming Language :: Python :: 3
Classifier: License :: OSI Approved :: MIT License
License-File: LICENSE
Requires-Dist: requests
Requires-Dist: pygments
